cli/__init__.py
cli/agent.py
cli/env.py
cli/identity.py
cli/readme.py
cli/register.py
fetchai/__init__.py
fetchai/cli.py
fetchai/communication.py
fetchai/fetch.py
fetchai/logger.py
fetchai/registration.py
fetchai/schema.py
fetchai/tests/__init__.py
fetchai/tests/conftest.py
fetchai/tests/test_communication.py
fetchai/tests/test_fetch.py
fetchai/tests/test_registration.py
fetchai-0.1.43.dist-info/licenses/LICENSE
fetchai-0.1.43.dist-info/METADATA
fetchai-0.1.43.dist-info/WHEEL
fetchai-0.1.43.dist-info/entry_points.txt
fetchai-0.1.43.dist-info/top_level.txt
fetchai-0.1.43.dist-info/RECORD
