Metadata-Version: 2.4
Name: fetchai
Version: 0.1.43
Summary: Find the right AI at the right time and register your AI to be discovered.
Home-page: https://github.com/flockx-official/fetchai
Author: Devon Bleibtrey
Author-email: bleib1dj@gmail.com
License: MIT
Classifier: Programming Language :: Python :: 3
Classifier: License :: OSI Approved :: MIT License
Classifier: Operating System :: OS Independent
Requires-Python: >=3.10,<4.0
License-File: LICENSE
Requires-Dist: uagents-core>=0.3.2
Requires-Dist: mnemonic>=0.21
Requires-Dist: click<9.0,>=8.1.2
Requires-Dist: python-dotenv>=1.0.1
Requires-Dist: agentverse-client>=0.1.2
Provides-Extra: dev
Requires-Dist: black==24.10.0; extra == "dev"
Requires-Dist: pytest==8.3.4; extra == "dev"
Requires-Dist: pytest-cov==6.0.0; extra == "dev"
Requires-Dist: requests-mock==1.12.1; extra == "dev"
Dynamic: author
Dynamic: author-email
Dynamic: classifier
Dynamic: description
Dynamic: description-content-type
Dynamic: home-page
Dynamic: license
Dynamic: license-file
Dynamic: provides-extra
Dynamic: requires-dist
Dynamic: requires-python
Dynamic: summary
